passfx/__init__.py
passfx/__main__.py
passfx/app.py
passfx/cli.py
passfx/core/__init__.py
passfx/core/config.py
passfx/core/crypto.py
passfx/core/models.py
passfx/core/vault.py
passfx/screens/__init__.py
passfx/screens/cards.py
passfx/screens/envs.py
passfx/screens/generator.py
passfx/screens/help.py
passfx/screens/login.py
passfx/screens/main_menu.py
passfx/screens/notes.py
passfx/screens/passwords.py
passfx/screens/phones.py
passfx/screens/recovery.py
passfx/screens/settings.py
passfx/search/__init__.py
passfx/search/config.py
passfx/search/engine.py
passfx/styles/passfx.tcss
passfx/ui/__init__.py
passfx/ui/logo.py
passfx/ui/menu.py
passfx/ui/styles.py
passfx/utils/__init__.py
passfx/utils/clipboard.py
passfx/utils/generator.py
passfx/utils/io.py
passfx/utils/platform_security.py
passfx/utils/strength.py
passfx/widgets/__init__.py
passfx/widgets/id_card_modal.py
passfx/widgets/keycap_footer.py
passfx/widgets/matrix_rain.py
passfx/widgets/search_overlay.py
passfx/widgets/terminal.py
passfx-1.0.3.dist-info/METADATA
passfx-1.0.3.dist-info/WHEEL
passfx-1.0.3.dist-info/entry_points.txt
passfx-1.0.3.dist-info/licenses/LICENSE
passfx-1.0.3.dist-info/RECORD
