Metadata-Version: 2.4
Name: passfx
Version: 1.0.3
Summary: A secure, stylish terminal password manager. Your secrets are safe with us. Probably.
Project-URL: Homepage, https://passfx.dineshd.dev
Project-URL: Documentation, https://github.com/dinesh-git17/passfx/tree/main/docs
Project-URL: Repository, https://github.com/dinesh-git17/passfx
Project-URL: Issues, https://github.com/dinesh-git17/passfx/issues
Project-URL: Changelog, https://github.com/dinesh-git17/passfx/blob/main/docs/CHANGELOG.md
Author-email: PassFX Team <info@dineshd.dev>
License-Expression: MIT
License-File: LICENSE
Keywords: cli,encryption,manager,password,security
Classifier: Development Status :: 4 - Beta
Classifier: Environment :: Console
Classifier: Intended Audience :: Developers
Classifier: License :: OSI Approved :: MIT License
Classifier: Operating System :: OS Independent
Classifier: Programming Language :: Python :: 3
Classifier: Programming Language :: Python :: 3.10
Classifier: Programming Language :: Python :: 3.11
Classifier: Programming Language :: Python :: 3.12
Classifier: Topic :: Security
Classifier: Topic :: Utilities
Requires-Python: >=3.10
Requires-Dist: cryptography<47.0.0,>=46.0.0
Requires-Dist: pyperclip<2.0.0,>=1.11.0
Requires-Dist: rich<15.0.0,>=14.0.0
Requires-Dist: setproctitle<2.0.0,>=1.3.7
Requires-Dist: simple-term-menu<2.0.0,>=1.6.6
Requires-Dist: textual<7.0.0,>=6.11.0
Requires-Dist: zxcvbn<5.0.0,>=4.5.0
Provides-Extra: dev
Requires-Dist: bandit<2.0.0,>=1.9.0; extra == 'dev'
Requires-Dist: mypy<2.0.0,>=1.19.0; extra == 'dev'
Requires-Dist: pytest-cov<8.0.0,>=6.0.0; extra == 'dev'
Requires-Dist: pytest-timeout<3.0.0,>=2.3.0; extra == 'dev'
Requires-Dist: pytest-xdist<4.0.0,>=3.5.0; extra == 'dev'
Requires-Dist: pytest<10.0.0,>=8.0.0; extra == 'dev'
Requires-Dist: ruff<1.0.0,>=0.14.0; extra == 'dev'
Requires-Dist: textual-dev<2.0.0,>=1.0.0; extra == 'dev'
Requires-Dist: types-pyperclip<2.0.0,>=1.9.0; extra == 'dev'
Requires-Dist: types-zxcvbn<5.0.0,>=4.5.0; extra == 'dev'
